{
  "role-name": "Plaguebearer",

  "alignment": "neutral",
  "class": "chaos",

  "see-mafia-chat": false,

  "stats": {
    "basic-defense": 1,
    "roleblock-immunity": 0,
    "detection-immunity": 1,
    "control-immunity": 0,
		"redirection-immunity": 0,
		"kidnap-immunity": 0,
    "priority": 9,
    "vote-offset": 0,
		"vote-magnitude": 1
  },

  "investigation": ["Plaguebearer"],
  "secondary-roles": null,

  "tags": [],

  "reveal-role-on-interrogation": false,

  "win-condition": "epipestilence"
}
